django_url_sso-0.9.dist-info/DESCRIPTION.rst
django_url_sso-0.9.dist-info/METADATA
django_url_sso-0.9.dist-info/pydist.json
django_url_sso-0.9.dist-info/RECORD
django_url_sso-0.9.dist-info/top_level.txt
django_url_sso-0.9.dist-info/WHEEL
url_sso/__init__.py
url_sso/context_processors.py
url_sso/exceptions.py
url_sso/models.py
url_sso/settings.py
url_sso/utils.py
url_sso/views.py
url_sso/plugins/__init__.py
url_sso/plugins/base.py
url_sso/plugins/intershift.py
url_sso/plugins/iprova.py
url_sso/tests/__init__.py
url_sso/tests/__init__.pyc
url_sso/tests/context_processor.py
url_sso/tests/context_processor.pyc
url_sso/tests/mock_plugins.py
url_sso/tests/mock_plugins.pyc
url_sso/tests/utils.py
url_sso/tests/utils.pyc
url_sso/tests/data/iprova_token_response.xml
url_sso/tests/data/iprova_usermanagement_wsdl.xml
url_sso/tests/plugins/__init__.py
url_sso/tests/plugins/__init__.pyc
url_sso/tests/plugins/base.py
url_sso/tests/plugins/base.pyc
url_sso/tests/plugins/intershift.py
url_sso/tests/plugins/intershift.pyc
url_sso/tests/plugins/iprova.py
url_sso/tests/plugins/iprova.pyc
