Metadata-Version: 2.0
Name: django-url-sso
Version: 0.9
Summary: Generate login URL's for unstandardized SSO systems.
Home-page: https://github.com/visualspace/django-url-sso/
Author: Mathijs de Bruin
Author-email: mathijs@visualspace.nl
License: AGPL
Platform: UNKNOWN
Classifier: Development Status :: 5 - Production/Stable
Classifier: Environment :: Web Environment
Classifier: Framework :: Django
Classifier: Intended Audience :: Developers
Classifier: License :: OSI Approved :: GNU Affero General Public License v3
Classifier: Operating System :: OS Independent
Classifier: Programming Language :: Python
Classifier: Topic :: Utilities
Requires-Dist: Django (>=1.4.10)
Requires-Dist: requests
Requires-Dist: httmock
Requires-Dist: lxml
Requires-Dist: suds
Requires-Dist: suds-requests
Requires-Dist: mock
